{"type": "FeatureCollection", "features": [{"type": "Feature", "geometry": {"coordinates": [28.3111262, -28.2423025], "type": "Point"}, "properties": {"name": "Child & Family Welfare in Bethlehem (23)", "actualname": "Child & Family Welfare", "subregion": "Bethlehem", "beds": "23"}}, {"type": "Feature", "geometry": {"coordinates": [27.4908738, -26.9110891], "type": "Point"}, "properties": {"name": "Tumahole Victim Support Centre  in Parys (23)", "actualname": "Tumahole Victim Support Centre ", "subregion": "Parys", "beds": "23"}}, {"type": "Feature", "geometry": {"coordinates": [28.824722, -28.5530273], "type": "Point"}, "properties": {"name": "Thusanang Advice Centre Shelter  in Qwaqwa (23)", "actualname": "Thusanang Advice Centre Shelter ", "subregion": "Qwaqwa", "beds": "23"}}, {"type": "Feature", "geometry": {"coordinates": [26.7732162, -28.0045655], "type": "Point"}, "properties": {"name": "Goldfields Family Advice Organisation in Welkom (23)", "actualname": "Goldfields Family Advice Organisation", "subregion": "Welkom", "beds": "23"}}], "name": "FS"}